aws_static_website/__init__.py
aws_static_website/website_stack.py
tests/__init__.py
tests/test_website_stack.py
aws_static_website-0.0.3.dist-info/LICENSE
aws_static_website-0.0.3.dist-info/METADATA
aws_static_website-0.0.3.dist-info/WHEEL
aws_static_website-0.0.3.dist-info/top_level.txt
aws_static_website-0.0.3.dist-info/RECORD
